README.rst
setup.cfg
setup.py
xin/__init__.py
xin/bb/__init__.py
xin/bb/tools.py
xin/bb/model_util/__init__.py
xin/bb/model_util/controller.py
xin/bb/model_util/fields.py
xin/bb/model_util/model.py
xin/bb/model_util/searcher.py
xin/bb/model_util/version.py
xin/bb/rest/__init__.py
xin/bb/view_util/__init__.py
xin/bb/view_util/fields.py
xin/bb/view_util/history_api.py
xin/bb/view_util/schema.py
xin/components/__init__.py
xin/components/authentic/__init__.py
xin/components/authentic/authentic.py
xin/components/authentic/config.py
xin/components/authentic/rest.py
xin/components/authentic/tools.py
xin/components/butler/__init__.py
xin/components/butler/butler.py
xin/components/butler/launcher_butler.py
xin/components/kalendar/__init__.py
xin/components/kalendar/app.py
xin/components/kalendar/model/__init__.py
xin/components/kalendar/model/calendar_model.py
xin/components/kalendar/model/database.py
xin/components/kalendar/model/meeting.py
xin/components/kalendar/tests/__init__.py
xin/components/kalendar/tests/common.py
xin/components/kalendar/tests/test_calendar_api.py
xin/components/kalendar/tests/test_meeting_api.py
xin/components/kalendar/view/__init__.py
xin/components/kalendar/view/calendar_api.py
xin/components/kalendar/view/meeting_api.py
xin_back.egg-info/PKG-INFO
xin_back.egg-info/SOURCES.txt
xin_back.egg-info/dependency_links.txt
xin_back.egg-info/not-zip-safe
xin_back.egg-info/requires.txt
xin_back.egg-info/top_level.txt