Metadata-Version: 1.1
Name: xin-back
Version: 0.4.1
Summary: UNKNOWN
Home-page: https://github.com/Scille/xin-back
Author: Scille
Author-email: contact@scille.fr
License: MIT
Platform: UNKNOWN
Classifier: Intended Audience :: Developers
Classifier: Natural Language :: English
Classifier: Programming Language :: Python :: 3
Classifier: Programming Language :: Python :: 3.3
Classifier: Programming Language :: Python :: 3.4
Classifier: Programming Language :: Python :: 3.5
